{
  "openViewOnStart": true,
  "ribbonIcon": true,
  "showRootFolder": false,
  "showFilesFromSubFolders": true,
  "searchFunction": true,
  "allSearchOnlyInFocusedFolder": false,
  "showFilesFromSubFoldersButton": true,
  "revealActiveFileButton": false,
  "excludedExtensions": "",
  "excludedFolders": "node_modules",
  "folderIcon": "default",
  "folderCount": true,
  "folderCountOption": "notes",
  "evernoteView": "Vertical",
  "filePreviewOnHover": false,
  "iconBeforeFileName": true,
  "sortFilesBy": "created",
  "sortReverse": false,
  "sortFoldersBy": "name",
  "fixedHeaderInFileList": true,
  "createdYaml": false,
  "fileNameIsHeader": false,
  "folderNote": false,
  "deleteFileOption": "trash",
  "showFileNameAsFullPath": false
}